MANIFEST.in
README.md
VERSION
__init__.py
py.typed
pyproject.toml
results.py
setup.py
./__init__.py
./py.typed
./results.py
./setup.py
./tools/__init__.py
./tools/analysis.py
./tools/base.py
./tools/filters.py
tools/__init__.py
tools/analysis.py
tools/base.py
tools/filters.py
vcfx.egg-info/PKG-INFO
vcfx.egg-info/SOURCES.txt
vcfx.egg-info/dependency_links.txt
vcfx.egg-info/not-zip-safe
vcfx.egg-info/top_level.txt