Metadata-Version: 2.4
Name: vcfx
Version: 1.1.3
Summary: Python bindings for the VCFX toolkit - comprehensive VCF manipulation and analysis
Author: Jorge Miguel Silva, José Luis Oliveira
License-Expression: MIT
Project-URL: Homepage, https://github.com/ieeta-pt/VCFX
Project-URL: Documentation, https://ieeta-pt.github.io/VCFX/
Project-URL: Repository, https://github.com/ieeta-pt/VCFX.git
Project-URL: Bug Tracker, https://github.com/ieeta-pt/VCFX/issues
Keywords: vcf,bioinformatics,genomics,variant-analysis,python-bindings
Classifier: Development Status :: 5 - Production/Stable
Classifier: Intended Audience :: Science/Research
Classifier: Topic :: Scientific/Engineering :: Bio-Informatics
Classifier: Programming Language :: Python :: 3
Classifier: Programming Language :: Python :: 3.10
Classifier: Programming Language :: Python :: 3.11
Classifier: Programming Language :: Python :: 3.12
Classifier: Programming Language :: C++
Classifier: Operating System :: MacOS :: MacOS X
Classifier: Operating System :: POSIX :: Linux
Requires-Python: >=3.10
